webarchive/__init__.py
webarchive/exceptions.py
webarchive/test.py
webarchive/util.py
webarchive/webarchive.py
webarchive/webresource.py
pywebarchive-0.5.2.dist-info/LICENSE
pywebarchive-0.5.2.dist-info/METADATA
pywebarchive-0.5.2.dist-info/WHEEL
pywebarchive-0.5.2.dist-info/top_level.txt
pywebarchive-0.5.2.dist-info/RECORD
